gcp_storage_emulator/__init__.py
gcp_storage_emulator/__main__.py
gcp_storage_emulator/exceptions.py
gcp_storage_emulator/server.py
gcp_storage_emulator/settings.py
gcp_storage_emulator/storage.py
gcp_storage_emulator/handlers/__init__.py
gcp_storage_emulator/handlers/buckets.py
gcp_storage_emulator/handlers/objects.py
gcp_storage_emulator-2024.8.3.dist-info/LICENCE.md
gcp_storage_emulator-2024.8.3.dist-info/METADATA
gcp_storage_emulator-2024.8.3.dist-info/WHEEL
gcp_storage_emulator-2024.8.3.dist-info/entry_points.txt
gcp_storage_emulator-2024.8.3.dist-info/top_level.txt
gcp_storage_emulator-2024.8.3.dist-info/RECORD
