Metadata-Version: 2.1
Name: gcp-storage-emulator
Version: 2024.8.3
Summary: A stub emulator for the Google Cloud Storage API
Home-page: https://github.com/oittaa/gcp-storage-emulator
Author: Eero Vuojolahti
Author-email: contact@oittaa.com
Keywords: Google Cloud Storage,Google App Engine,Google Cloud Platform,GCS,GAE,GCP
Classifier: Development Status :: 3 - Alpha
Classifier: Intended Audience :: Developers
Classifier: License :: OSI Approved :: BSD License
Classifier: Operating System :: OS Independent
Classifier: Programming Language :: Python
Classifier: Programming Language :: Python :: 3
Classifier: Programming Language :: Python :: 3.8
Classifier: Programming Language :: Python :: 3.9
Classifier: Programming Language :: Python :: 3.10
Classifier: Programming Language :: Python :: 3.11
Classifier: Programming Language :: Python :: 3.12
Requires-Python: >=3.8
License-File: LICENCE.md
Requires-Dist: fs
Requires-Dist: google-crc32c
